[{
  "dateTime" : "03/27/22 00:00:00",
  "value" : "137"
},{
  "dateTime" : "03/28/22 00:00:00",
  "value" : "226"
},{
  "dateTime" : "03/29/22 00:00:00",
  "value" : "252"
},{
  "dateTime" : "03/30/22 00:00:00",
  "value" : "252"
},{
  "dateTime" : "03/31/22 00:00:00",
  "value" : "184"
},{
  "dateTime" : "04/01/22 00:00:00",
  "value" : "186"
},{
  "dateTime" : "04/02/22 00:00:00",
  "value" : "115"
},{
  "dateTime" : "04/03/22 00:00:00",
  "value" : "148"
},{
  "dateTime" : "04/04/22 00:00:00",
  "value" : "124"
},{
  "dateTime" : "04/05/22 00:00:00",
  "value" : "193"
},{
  "dateTime" : "04/06/22 00:00:00",
  "value" : "168"
},{
  "dateTime" : "04/07/22 00:00:00",
  "value" : "137"
},{
  "dateTime" : "04/08/22 00:00:00",
  "value" : "196"
},{
  "dateTime" : "04/09/22 00:00:00",
  "value" : "83"
},{
  "dateTime" : "04/10/22 00:00:00",
  "value" : "63"
},{
  "dateTime" : "04/11/22 00:00:00",
  "value" : "155"
},{
  "dateTime" : "04/12/22 00:00:00",
  "value" : "212"
},{
  "dateTime" : "04/13/22 00:00:00",
  "value" : "177"
},{
  "dateTime" : "04/14/22 00:00:00",
  "value" : "250"
},{
  "dateTime" : "04/15/22 00:00:00",
  "value" : "249"
},{
  "dateTime" : "04/16/22 00:00:00",
  "value" : "212"
},{
  "dateTime" : "04/17/22 00:00:00",
  "value" : "187"
},{
  "dateTime" : "04/18/22 00:00:00",
  "value" : "253"
},{
  "dateTime" : "04/19/22 00:00:00",
  "value" : "187"
},{
  "dateTime" : "04/20/22 00:00:00",
  "value" : "217"
},{
  "dateTime" : "04/21/22 00:00:00",
  "value" : "210"
},{
  "dateTime" : "04/22/22 00:00:00",
  "value" : "227"
},{
  "dateTime" : "04/23/22 00:00:00",
  "value" : "148"
},{
  "dateTime" : "04/24/22 00:00:00",
  "value" : "78"
},{
  "dateTime" : "04/25/22 00:00:00",
  "value" : "0"
}]