{"userProfileId": 103595922, "totalKilocalories": 2113.0, "activeKilocalories": 237.0, "bmrKilocalories": 1876.0, "wellnessKilocalories": 2113.0, "burnedKilocalories": null, "consumedKilocalories": null, "remainingKilocalories": 2113.0, "totalSteps": 3628, "netCalorieGoal": 2411, "totalDistanceMeters": 2912, "wellnessDistanceMeters": 3165, "wellnessActiveKilocalories": 237.0, "netRemainingKilocalories": 2648.0, "userDailySummaryId": 103595922, "calendarDate": "2022-04-02", "rule": {"typeId": 2, "typeKey": "private"}, "uuid": "33ddabfab0724843ad9d046979b593c5", "dailyStepGoal": 6520, "wellnessStartTimeGmt": "2022-04-01T23:00:00.0", "wellnessStartTimeLocal": "2022-04-02T00:00:00.0", "wellnessEndTimeGmt": "2022-04-02T23:00:00.0", "wellnessEndTimeLocal": "2022-04-03T00:00:00.0", "durationInMilliseconds": 86400000, "wellnessDescription": null, "highlyActiveSeconds": 1065, "activeSeconds": 2747, "sedentarySeconds": 50788, "sleepingSeconds": 31800, "includesWellnessData": true, "includesActivityData": false, "includesCalorieConsumedData": false, "privacyProtected": false, "moderateIntensityMinutes": 0, "vigorousIntensityMinutes": 0, "floorsAscendedInMeters": 7.721, "floorsDescendedInMeters": 0.0, "floorsAscended": 2.53314, "floorsDescended": 0.0, "intensityMinutesGoal": 150, "userFloorsAscendedGoal": 10, "minHeartRate": 47, "maxHeartRate": 136, "restingHeartRate": 60, "lastSevenDaysAvgRestingHeartRate": 60, "source": "GARMIN", "averageStressLevel": 34, "maxStressLevel": 96, "stressDuration": 33900, "restStressDuration": 35580, "activityStressDuration": 9360, "uncategorizedStressDuration": 3600, "totalStressDuration": 82440, "lowStressDuration": 11160, "mediumStressDuration": 13080, "highStressDuration": 9660, "stressPercentage": 41.12, "restStressPercentage": 43.16, "activityStressPercentage": 11.35, "uncategorizedStressPercentage": 4.37, "lowStressPercentage": 13.54, "mediumStressPercentage": 15.87, "highStressPercentage": 11.72, "stressQualifier": "BALANCED", "measurableAwakeDuration": 48480, "measurableAsleepDuration": 30360, "lastSyncTimestampGMT": null, "minAvgHeartRate": 48, "maxAvgHeartRate": 127, "bodyBatteryChargedValue": 107, "bodyBatteryDrainedValue": 89, "bodyBatteryHighestValue": 100, "bodyBatteryLowestValue": 20, "bodyBatteryMostRecentValue": 41, "bodyBatteryVersion": 1.0, "abnormalHeartRateAlertsCount": null, "averageSpo2": 99.0, "lowestSpo2": 95, "latestSpo2": 99, "latestSpo2ReadingTimeGmt": "2022-04-02T04:07:00.0", "latestSpo2ReadingTimeLocal": "2022-04-02T05:07:00.0", "averageMonitoringEnvironmentAltitude": null, "restingCaloriesFromActivity": null, "avgWakingRespirationValue": 13.0, "highestRespirationValue": 18.0, "lowestRespirationValue": 9.0, "latestRespirationValue": 18.0, "latestRespirationTimeGMT": "2022-04-02T23:00:00.0"}